durc_is_crud/__init__.py
durc_is_crud/management/__init__.py
durc_is_crud/management/commands/__init__.py
durc_is_crud/management/commands/durc_compile.py
durc_is_crud/management/commands/durc_mine.py
durc_is_crud/management/commands/durc_utils/__init__.py
durc_is_crud/management/commands/durc_utils/data_type_mapper.py
durc_is_crud/management/commands/durc_utils/include_pattern_parser.py
durc_is_crud/management/commands/durc_utils/relational_model_extractor.py
durc_is_crud-0.1.0.dist-info/licenses/LICENSE
durc_is_crud-0.1.0.dist-info/METADATA
durc_is_crud-0.1.0.dist-info/WHEEL
durc_is_crud-0.1.0.dist-info/top_level.txt
durc_is_crud-0.1.0.dist-info/RECORD
