Metadata-Version: 2.4
Name: durc_is_crud
Version: 0.1.0
Summary: A package for Database to CRUD operations
Home-page: https://github.com/ftrotter/durc_is_crud
Author: Fred Trotter
Author-email: fred@example.com
Project-URL: Bug Reports, https://github.com/ftrotter/durc_is_crud/issues
Project-URL: Source, https://github.com/ftrotter/durc_is_crud
Project-URL: Documentation, https://github.com/ftrotter/durc_is_crud/tree/main/docs
Classifier: Programming Language :: Python :: 3
Classifier: Programming Language :: Python :: 3.6
Classifier: Programming Language :: Python :: 3.7
Classifier: Programming Language :: Python :: 3.8
Classifier: Programming Language :: Python :: 3.9
Classifier: License :: OSI Approved :: MIT License
Classifier: Operating System :: OS Independent
Classifier: Framework :: Django
Classifier: Framework :: Django :: 3.0
Classifier: Framework :: Django :: 3.1
Classifier: Framework :: Django :: 3.2
Classifier: Framework :: Django :: 4.0
Classifier: Intended Audience :: Developers
Classifier: Topic :: Software Development :: Libraries :: Python Modules
Classifier: Topic :: Database
Requires-Python: >=3.6
License-File: LICENSE
Requires-Dist: django>=3.0.0
Requires-Dist: pytest>=6.0.0
Requires-Dist: pytest-django>=4.0.0
Provides-Extra: dev
Requires-Dist: black; extra == "dev"
Requires-Dist: isort; extra == "dev"
Requires-Dist: flake8; extra == "dev"
Requires-Dist: coverage; extra == "dev"
Dynamic: author
Dynamic: author-email
Dynamic: classifier
Dynamic: description
Dynamic: description-content-type
Dynamic: home-page
Dynamic: license-file
Dynamic: project-url
Dynamic: provides-extra
Dynamic: requires-dist
Dynamic: requires-python
Dynamic: summary
